junkdetect/__init__.py
junkdetect/__main__.py
junkdetect/perplex.py
junkdetect-0.1.2.dist-info/LICENSE
junkdetect-0.1.2.dist-info/METADATA
junkdetect-0.1.2.dist-info/WHEEL
junkdetect-0.1.2.dist-info/entry_points.txt
junkdetect-0.1.2.dist-info/top_level.txt
junkdetect-0.1.2.dist-info/RECORD
