Metadata-Version: 2.1
Name: junkdetect
Version: 0.1.2
Summary: Junk Not-Junk Detector
Home-page: https://github.com/thammegowda/junkdetect
Author: Thamme Gowda
Author-email: tgowdan@gmail.com
License: Apache Software License 2.0
Download-URL: https://github.com/thammegowda/junkdetect
Platform: any
Classifier: Development Status :: 5 - Production/Stable
Classifier: Intended Audience :: Developers
Classifier: Topic :: Text Processing
Classifier: Topic :: Utilities
Classifier: Topic :: Text Processing :: General
Classifier: Topic :: Text Processing :: Filters
Classifier: License :: OSI Approved :: Apache Software License
Classifier: Programming Language :: Python :: 3
Requires-Python: >=3.6
Requires-Dist: requests
Requires-Dist: sentencepiece
Requires-Dist: torch (>=1.3)
Requires-Dist: regex
Requires-Dist: tqdm
